confuse_jsonschema/__init__.py
confuse_jsonschema/templates.py
confuse_jsonschema/to_template.py
confuse_jsonschema-0.1.0.dist-info/licenses/LICENSE
confuse_jsonschema-0.1.0.dist-info/METADATA
confuse_jsonschema-0.1.0.dist-info/WHEEL
confuse_jsonschema-0.1.0.dist-info/top_level.txt
confuse_jsonschema-0.1.0.dist-info/RECORD
