Metadata-Version: 2.4
Name: confuse-jsonschema
Version: 0.1.0
Summary: Convert JSON Schema to Confuse templates
Author-email: Christophe-Marie Duquesne <chmd@chmd.fr>
License-Expression: MIT
Project-URL: Homepage, https://github.com/chmduquesne/confuse-jsonschema
Project-URL: Repository, https://github.com/chmduquesne/confuse-jsonschema
Project-URL: Issues, https://github.com/chmduquesne/confuse-jsonschema/issues
Keywords: json,schema,confuse,configuration,yaml
Classifier: Development Status :: 3 - Alpha
Classifier: Intended Audience :: Developers
Classifier: Programming Language :: Python :: 3
Classifier: Programming Language :: Python :: 3.8
Classifier: Programming Language :: Python :: 3.9
Classifier: Programming Language :: Python :: 3.10
Classifier: Programming Language :: Python :: 3.11
Classifier: Programming Language :: Python :: 3.12
Classifier: Topic :: Software Development :: Libraries :: Python Modules
Requires-Python: >=3.8
License-File: LICENSE
Requires-Dist: confuse>=1.7.0
Requires-Dist: jsonschema>=4.0.0
Provides-Extra: dev
Requires-Dist: pytest>=7.0.0; extra == "dev"
Requires-Dist: pytest-cov>=4.0.0; extra == "dev"
Requires-Dist: black>=23.0.0; extra == "dev"
Requires-Dist: flake8>=6.0.0; extra == "dev"
Requires-Dist: mypy>=1.0.0; extra == "dev"
Requires-Dist: build>=1.3.0; extra == "dev"
Requires-Dist: twine>=6.2.0; extra == "dev"
Dynamic: license-file
